simplesettings_py/__init__.py
simplesettings_py/settings.py
simplesettings_py-1.0.4.dist-info/LICENSE
simplesettings_py-1.0.4.dist-info/METADATA
simplesettings_py-1.0.4.dist-info/WHEEL
simplesettings_py-1.0.4.dist-info/top_level.txt
simplesettings_py-1.0.4.dist-info/RECORD
