Metadata-Version: 2.1
Name: simplesettings-py
Version: 1.0.4
Summary: Python settings files done simple.
Author-email: Stuntlover <stuntlover@aluvia.de>
Project-URL: Homepage, https://github.com/Stuntlover-TM/simplesettings
Project-URL: Bug Tracker, https://github.com/Stuntlover-TM/simplesettings/issues
Classifier: Programming Language :: Python :: 3
Classifier: License :: OSI Approved :: MIT License
Classifier: Operating System :: OS Independent
Requires-Python: >=3.9
License-File: LICENSE
